pysdk/Library.py
pysdk/__init__.py
wallet_pysdk-1.0.1.dist-info/METADATA
wallet_pysdk-1.0.1.dist-info/WHEEL
wallet_pysdk-1.0.1.dist-info/top_level.txt
wallet_pysdk-1.0.1.dist-info/RECORD
