Metadata-Version: 2.1
Name: wallet-pysdk
Version: 1.0.1
Summary: open api
Home-page: https://github.com/walletcloud88/pysdk
Author: JZ浩
Author-email: walletcloud88@gmail.com
Classifier: Programming Language :: Python :: 3
Classifier: License :: OSI Approved :: MIT License
Classifier: Operating System :: OS Independent
Requires-Python: >=3.6
Requires-Dist: pycryptodome >=3.21.0
Requires-Dist: requests >=2.32.3
